{"result": [{"interval": [304.44, 305.39], "word": "[*]"}, {"interval": [305.58, 306.02], "word": "mit"}, {"interval": [306.02, 306.36], "word": "einer"}, {"interval": [306.36, 307.04], "word": "negativen"}, {"interval": [307.04, 307.5], "word": "Erfahrung"}, {"interval": [307.5, 308.28], "word": "verbunden."}, {"interval": [308.76, 309.14], "word": "[*]"}, {"interval": [309.27, 309.91], "word": "Lassen"}, {"interval": [309.91, 309.99], "word": "Sie"}, {"interval": [309.99, 310.13], "word": "mich"}, {"interval": [310.13, 310.25], "word": "die"}, {"interval": [310.25, 310.99], "word": "wichtigsten"}, {"interval": [310.99, 311.33], "word": "Punkte"}]}